{
  "name": "continue writing",
  "trigger": "new-line",
  "pattern": "M0,1 L3,1 L2,0 L3,1 L2,2",
  "mode": "append",
  "actions": [
    {
      "type": "generate",
      "template": "Continue the following story, which is delimited with triple backticks. Follow up the event prompted in the last sentence or paragraph or just go for a complete different and unexpected direction. \n\nContinue the story in a narrative way, keeping the style of the story. Keep your answer as short as possible and use one short sentence.\n\nStory: ```::full::```"
    }
  ]
}
